spepper/__init__.py
spepper-0.0.1.dist-info/METADATA
spepper-0.0.1.dist-info/WHEEL
spepper-0.0.1.dist-info/top_level.txt
spepper-0.0.1.dist-info/RECORD
